term_piechart/__init__.py
term_piechart/color.py
term_piechart/pie.py
term_piechart/slice.py
term_piechart-0.1.3.dist-info/METADATA
term_piechart-0.1.3.dist-info/WHEEL
term_piechart-0.1.3.dist-info/licenses/LICENSE
term_piechart-0.1.3.dist-info/RECORD
