Metadata-Version: 2.3
Name: term-piechart
Version: 0.1.3
Summary: Library to print piecharts in your terminal
Project-URL: Changelog, https://github.com/va-h/term-piechart/releases
Project-URL: Homepage, https://github.com/va-h/term-piechart
Project-URL: Source, https://github.com/va-h/term-piechart
License: MIT
License-File: LICENSE
Classifier: Environment :: Console
Classifier: License :: OSI Approved :: MIT License
Classifier: Programming Language :: Python :: 3
Classifier: Programming Language :: Python :: 3.7
Classifier: Programming Language :: Python :: 3.8
Classifier: Programming Language :: Python :: 3.9
Classifier: Programming Language :: Python :: 3.10
Classifier: Programming Language :: Python :: 3.11
Classifier: Programming Language :: Python :: 3.12
Classifier: Topic :: Terminals
Requires-Python: >=3.7
Provides-Extra: dev
Requires-Dist: pytest; extra == 'dev'
Requires-Dist: pytest-cov; extra == 'dev'
